subdomains/__init__.py
subdomains/middleware.py
subdomains/models.py
subdomains/utils.py
subdomains/templatetags/__init__.py
subdomains/templatetags/subdomainurls.py
subdomains/tests/__init__.py
subdomains/tests/tests.py
subdomains/tests/views.py
subdomains/tests/urls/__init__.py
subdomains/tests/urls/api.py
subdomains/tests/urls/application.py
subdomains/tests/urls/default.py
subdomains/tests/urls/marketing.py
subdomains-2.1.1.dist-info/DESCRIPTION.rst
subdomains-2.1.1.dist-info/METADATA
subdomains-2.1.1.dist-info/RECORD
subdomains-2.1.1.dist-info/WHEEL
subdomains-2.1.1.dist-info/metadata.json
subdomains-2.1.1.dist-info/top_level.txt
