Metadata-Version: 2.0
Name: subdomains
Version: 2.1.1
Summary: Subdomain tools for the Django framework, including subdomain-based URL routing.
Home-page: http://github.com/abe312/django-subdomains/
Author: abe312
Author-email: abhineet312@gmail.com
License: MIT License
Platform: UNKNOWN
Requires-Dist: django
